moderndid/__init__.py
moderndid/_version.py
moderndid/core/__init__.py
moderndid/core/data.py
moderndid/core/dataframe.py
moderndid/core/preprocessing.py
moderndid/core/datasets/__init__.py
moderndid/core/datasets/ehec_data.pkl.gz
moderndid/core/datasets/engel.pkl.gz
moderndid/core/datasets/mpdta_long.pkl.gz
moderndid/core/datasets/nsw_long.pkl.gz
moderndid/core/preprocess/__init__.py
moderndid/core/preprocess/base.py
moderndid/core/preprocess/builders.py
moderndid/core/preprocess/config.py
moderndid/core/preprocess/constants.py
moderndid/core/preprocess/models.py
moderndid/core/preprocess/tensors.py
moderndid/core/preprocess/transformers.py
moderndid/core/preprocess/utils.py
moderndid/core/preprocess/validators.py
moderndid/did/README.md
moderndid/did/__init__.py
moderndid/did/aggte.py
moderndid/did/aggte_obj.py
moderndid/did/att_gt.py
moderndid/did/compute_aggte.py
moderndid/did/compute_att_gt.py
moderndid/did/mboot.py
moderndid/did/multiperiod_obj.py
moderndid/did/plots/__init__.py
moderndid/did/plots/core.py
moderndid/did/plots/methods.py
moderndid/did2s/README.md
moderndid/did2s/__init__.py
moderndid/didbacon/README.md
moderndid/didbacon/__init__.py
moderndid/didcomp/README.md
moderndid/didcomp/__init__.py
moderndid/didcont/README.md
moderndid/didcont/__init__.py
moderndid/didcont/cont_did.py
moderndid/didcont/numba.py
moderndid/didcont/utils.py
moderndid/didcont/estimation/__init__.py
moderndid/didcont/estimation/bootstrap.py
moderndid/didcont/estimation/container.py
moderndid/didcont/estimation/estimators.py
moderndid/didcont/estimation/process_aggte.py
moderndid/didcont/estimation/process_attgt.py
moderndid/didcont/estimation/process_dose.py
moderndid/didcont/estimation/process_panel.py
moderndid/didcont/npiv/__init__.py
moderndid/didcont/npiv/cck_ucb.py
moderndid/didcont/npiv/confidence_bands.py
moderndid/didcont/npiv/estimators.py
moderndid/didcont/npiv/gsl_bspline.py
moderndid/didcont/npiv/lepski.py
moderndid/didcont/npiv/npiv.py
moderndid-0.0.3.dist-info/licenses/LICENSE
moderndid-0.0.3.dist-info/WHEEL
moderndid-0.0.3.dist-info/METADATA
moderndid-0.0.3.dist-info/RECORD
