Metadata-Version: 2.4
Name: moderndid
Version: 0.0.3
Summary: Modern difference-in-differences estimators.
Author-email: Jordan DeKlerk <jordan.deklerk@gmail.com>
Requires-Python: >=3.10
Classifier: Development Status :: 3 - Alpha
Classifier: Intended Audience :: Developers
Classifier: Intended Audience :: Science/Research
Classifier: Intended Audience :: Education
Classifier: License :: OSI Approved :: MIT License
Classifier: Operating System :: OS Independent
Classifier: Programming Language :: Python
Classifier: Programming Language :: Python :: 3
Classifier: Programming Language :: Python :: 3.10
Classifier: Programming Language :: Python :: 3.11
Classifier: Programming Language :: Python :: 3.12
Classifier: Programming Language :: Python :: 3.13
License-File: LICENSE
Requires-Dist: numpy>=1.22.0
Requires-Dist: scipy>=1.10.0,<1.16
Requires-Dist: pandas>=2.0.0
Requires-Dist: polars>=1.0.0
Requires-Dist: pyarrow>=8.0.0
Requires-Dist: formulaic>=0.6.0
Requires-Dist: statsmodels>=0.14.4
Requires-Dist: cvxpy[ecos]>=1.3.0
Requires-Dist: sympy>=1.14.0
Requires-Dist: numba>=0.57.0
Requires-Dist: plotnine>=0.14.0
Requires-Dist: pre-commit ; extra == "dev"
Requires-Dist: ruff>=0.11.7 ; extra == "dev"
Requires-Dist: mypy ; extra == "dev"
Requires-Dist: sphinx-book-theme ; extra == "doc"
Requires-Dist: myst-parser[linkify] ; extra == "doc"
Requires-Dist: myst-nb ; extra == "doc"
Requires-Dist: sphinx-copybutton ; extra == "doc"
Requires-Dist: numpydoc ; extra == "doc"
Requires-Dist: sphinx ; extra == "doc"
Requires-Dist: sphinx-design ; extra == "doc"
Requires-Dist: jupyter-sphinx ; extra == "doc"
Requires-Dist: pytest ; extra == "test"
Requires-Dist: pytest-cov ; extra == "test"
Requires-Dist: pyfixest>=0.30.2 ; extra == "test"
Project-URL: documentation, https://moderndid.readthedocs.io
Project-URL: source, https://github.com/jordandeklerk/moderndid
Project-URL: tracker, https://github.com/jordandeklerk/moderndid/issues
Provides-Extra: dev
Provides-Extra: doc
Provides-Extra: test
